BAClangUtils/RawTokenUtil.py
BAClangUtils/RawTokenUtilTest.py
BAClangUtils/ShellUtil.py
BAClangUtils/__init__.py
BAClangUtils-1.0.10.dist-info/LICENSE
BAClangUtils-1.0.10.dist-info/METADATA
BAClangUtils-1.0.10.dist-info/WHEEL
BAClangUtils-1.0.10.dist-info/top_level.txt
BAClangUtils-1.0.10.dist-info/RECORD
