Metadata-Version: 2.1
Name: BAClangUtils
Version: 1.0.10
Summary: Clang utils for parse Objective-C code
Home-page: https://github.com/BenArvin/BAClangUtils
Author: BenArvin
Author-email: benarvin93@outlook.com
License: UNKNOWN
Platform: UNKNOWN
Classifier: Programming Language :: Python :: 3
Classifier: License :: OSI Approved :: MIT License
Classifier: Operating System :: OS Independent
